mister_bump.py
mister_bump-1.3.0.dist-info/DESCRIPTION.rst
mister_bump-1.3.0.dist-info/METADATA
mister_bump-1.3.0.dist-info/RECORD
mister_bump-1.3.0.dist-info/WHEEL
mister_bump-1.3.0.dist-info/entry_points.txt
mister_bump-1.3.0.dist-info/metadata.json
mister_bump-1.3.0.dist-info/top_level.txt
