Metadata-Version: 2.0
Name: mister-bump
Version: 1.3.0
Summary: Increment (bump) git version numbers for a project.
Home-page: https://github.com/jongracecox/mister-bump
Author: Jon Grace-Cox
Author-email: jongracecox@gmail.com
License: UNKNOWN
Platform: UNKNOWN
